npeet_plus/__init__.py
npeet_plus/estimators.py
npeet_plus-0.2.0.dist-info/LICENSE.md
npeet_plus-0.2.0.dist-info/METADATA
npeet_plus-0.2.0.dist-info/WHEEL
npeet_plus-0.2.0.dist-info/top_level.txt
npeet_plus-0.2.0.dist-info/RECORD
