Metadata-Version: 2.1
Name: npeet-plus
Version: 0.2.0
Summary: Non-parametric entropy estimation toolbox plus additional features
Home-page: https://github.com/yourusername/npeet_plus
Author: Greg Ver Steeg
Author-email: Albert Buchard <albert.buchard@gmail.com>
Project-URL: Homepage, https://github.com/albertbuchard/npeet_plus
Project-URL: Issues, https://github.com/albertbuchard/npeet_plus/issues
Classifier: Programming Language :: Python :: 3
Classifier: License :: OSI Approved :: MIT License
Classifier: Operating System :: OS Independent
Requires-Python: >=3.6
License-File: LICENSE.md
Requires-Dist: numpy (>=1.18.0)
Requires-Dist: scipy (>=1.4.0)
Requires-Dist: scikit-learn (>=0.22.0)
